{
  "version": 2,
  "writtenAt": 1780411499539,
  "toolAggregates": {
    "read": {
      "tool": "read",
      "count": 483,
      "successCount": 483,
      "failureCount": 0,
      "totalDuration": 163933
    },
    "glob": {
      "tool": "glob",
      "count": 45,
      "successCount": 45,
      "failureCount": 0,
      "totalDuration": 1860
    },
    "question": {
      "tool": "question",
      "count": 3,
      "successCount": 3,
      "failureCount": 0,
      "totalDuration": 120023
    },
    "task": {
      "tool": "task",
      "count": 26,
      "successCount": 26,
      "failureCount": 0,
      "totalDuration": 7369963
    },
    "grep": {
      "tool": "grep",
      "count": 44,
      "successCount": 44,
      "failureCount": 0,
      "totalDuration": 12043
    },
    "write": {
      "tool": "write",
      "count": 2,
      "successCount": 2,
      "failureCount": 0,
      "totalDuration": 105
    },
    "bash": {
      "tool": "bash",
      "count": 441,
      "successCount": 441,
      "failureCount": 0,
      "totalDuration": 1351528
    },
    "background_output": {
      "tool": "background_output",
      "count": 19,
      "successCount": 19,
      "failureCount": 0,
      "totalDuration": 387428
    },
    "todowrite": {
      "tool": "todowrite",
      "count": 55,
      "successCount": 55,
      "failureCount": 0,
      "totalDuration": 2745
    },
    "call_omo_agent": {
      "tool": "call_omo_agent",
      "count": 4,
      "successCount": 4,
      "failureCount": 0,
      "totalDuration": 300772
    },
    "search": {
      "tool": "search",
      "count": 44,
      "successCount": 44,
      "failureCount": 0,
      "totalDuration": 879157
    },
    "edit": {
      "tool": "edit",
      "count": 54,
      "successCount": 54,
      "failureCount": 0,
      "totalDuration": 6198
    },
    "invalid": {
      "tool": "invalid",
      "count": 2,
      "successCount": 2,
      "failureCount": 0,
      "totalDuration": 35
    },
    "suggest_patch": {
      "tool": "suggest_patch",
      "count": 1,
      "successCount": 1,
      "failureCount": 0,
      "totalDuration": 29
    },
    "lsp_diagnostics": {
      "tool": "lsp_diagnostics",
      "count": 1,
      "successCount": 1,
      "failureCount": 0,
      "totalDuration": 17018
    },
    "knowledge_add": {
      "tool": "knowledge_add",
      "count": 1,
      "successCount": 1,
      "failureCount": 0,
      "totalDuration": 49
    }
  },
  "activeAgent": {
    "ses_178e189dfffe4D1vd3BAlugntC": "Atlas - Plan Executor",
    "ses_178dd7795ffe78UCewnoJjvwoP": "explore",
    "ses_178d61460ffetLfLdnzIJfx1V1": "Metis - Plan Consultant",
    "ses_178d5c3c1ffeFPqrXPM5DY1ogy": "explore",
    "ses_178d5c392ffedbvkUIQi46ijpu": "explore",
    "ses_178d5c360ffek2M3RX1EMGj1E2": "explore",
    "ses_178c78078ffePxLxRBVP3cFNg8": "Momus - Plan Critic",
    "ses_178bb5f9effeD79730cfx8SxAZ": "Momus - Plan Critic",
    "ses_178b53c12ffehdA46tGbzK70ws": "Sisyphus-Junior",
    "ses_178abd8f3ffeS4xgCbRlfLVMrv": "Sisyphus-Junior",
    "ses_178a941ecffe6SuctiUtqJDahX": "orchestrator",
    "ses_1789226a5ffeewrncTH4m5SLkH": "Sisyphus-Junior",
    "ses_1788542ccffed8DqqTG5Ro76AV": "Sisyphus-Junior",
    "ses_1787e7758ffeeC9gPa3G7StW5d": "Sisyphus-Junior",
    "ses_1787e7538ffeorwqm8aezrM1id": "Sisyphus-Junior",
    "ses_1787a80fbffeLlft4WmclFLxyF": "Sisyphus-Junior",
    "ses_17878a413ffeSkPhj22UNZZe3U": "oracle",
    "ses_178728cdcffeoyY4Mt10M7EAwQ": "Sisyphus-Junior",
    "ses_178676ecaffe7wpebhPkI370f9": "Sisyphus-Junior",
    "ses_178628648ffel4hmSIAf3etPy5": "Sisyphus-Junior",
    "ses_1786182dcffe69Zr7lZ4Kms518": "orchestrator",
    "ses_1785a3476ffelz6FA649fbhLXU": "oracle",
    "ses_1785a3199ffeLlqK2zWgwJgg1B": "Sisyphus-Junior",
    "ses_1785a2eafffeJ5yEIdkGOa81f2": "Sisyphus-Junior",
    "ses_1785993cfffeDUuXeczEd63fxd": "Sisyphus-Junior",
    "ses_17840457effeELX05ICmnKbr7n": "explore",
    "ses_178360d02ffe2mXxvL2pQOnKoh": "Sisyphus-Junior",
    "ses_1782a4defffeXFRU8kEhQPtEnC": "orchestrator",
    "ses_1776eacc3ffebuCoQfn4uXiCWf": "Sisyphus-Junior",
    "ses_1776d5536ffeYwa4LJORKdu0cI": "Sisyphus-Junior",
    "ses_1776cb0e9ffe6pbBzD6nEWFQQD": "coder",
    "ses_17751632affeOsNNROpeAqjFbt": "coder"
  },
  "delegationChains": {
    "ses_178e189dfffe4D1vd3BAlugntC": [
      {
        "from": "architect",
        "to": "Prometheus - Plan Builder",
        "timestamp": 1780383749098
      },
      {
        "from": "architect",
        "to": "Prometheus - Plan Builder",
        "timestamp": 1780384794747
      },
      {
        "from": "architect",
        "to": "Atlas - Plan Executor",
        "timestamp": 1780386212596
      },
      {
        "from": "architect",
        "to": "Atlas - Plan Executor",
        "timestamp": 1780388203656
      },
      {
        "from": "architect",
        "to": "Atlas - Plan Executor",
        "timestamp": 1780390094913
      },
      {
        "from": "architect",
        "to": "Atlas - Plan Executor",
        "timestamp": 1780390609063
      },
      {
        "from": "architect",
        "to": "Atlas - Plan Executor",
        "timestamp": 1780391357790
      },
      {
        "from": "architect",
        "to": "Atlas - Plan Executor",
        "timestamp": 1780392614420
      },
      {
        "from": "Atlas - Plan Executor",
        "to": "Sisyphus - Ultraworker",
        "timestamp": 1780392903491
      },
      {
        "from": "Sisyphus - Ultraworker",
        "to": "Atlas - Plan Executor",
        "timestamp": 1780393246696
      },
      {
        "from": "architect",
        "to": "Atlas - Plan Executor",
        "timestamp": 1780394169810
      },
      {
        "from": "architect",
        "to": "Atlas - Plan Executor",
        "timestamp": 1780407125080
      },
      {
        "from": "architect",
        "to": "Atlas - Plan Executor",
        "timestamp": 1780407777140
      },
      {
        "from": "architect",
        "to": "Atlas - Plan Executor",
        "timestamp": 1780407904866
      }
    ]
  },
  "agentSessions": {
    "ses_178e189dfffe4D1vd3BAlugntC": {
      "agentName": "Atlas - Plan Executor",
      "lastToolCallTime": 1780411499059,
      "lastAgentEventTime": 1780411305114,
      "delegationActive": true,
      "activeInvocationId": 17,
      "lastInvocationIdByAgent": {
        "Prometheus - Plan Builder": 7,
        "Atlas - Plan Executor": 17,
        "Sisyphus - Ultraworker": 6
      },
      "windows": {
        "Atlas - Plan Executor:17": {
          "id": 17,
          "agentName": "Atlas - Plan Executor",
          "startedAtMs": 1780411383245,
          "toolCalls": 9,
          "consecutiveErrors": 0,
          "hardLimitHit": false,
          "lastSuccessTimeMs": 1780411499501,
          "recentToolCalls": [
            {
              "tool": "background_output",
              "argsHash": 5171531004954595000,
              "timestamp": 1780411426725
            },
            {
              "tool": "read",
              "argsHash": 14254899607072068000,
              "timestamp": 1780411426957
            },
            {
              "tool": "read",
              "argsHash": 13163175421880248000,
              "timestamp": 1780411427189
            },
            {
              "tool": "read",
              "argsHash": 4515562977081941500,
              "timestamp": 1780411448767
            },
            {
              "tool": "bash",
              "argsHash": 17174139600023675000,
              "timestamp": 1780411449084
            },
            {
              "tool": "grep",
              "argsHash": 18353261373498802000,
              "timestamp": 1780411470487
            },
            {
              "tool": "bash",
              "argsHash": 3933109535808888000,
              "timestamp": 1780411470890
            },
            {
              "tool": "read",
              "argsHash": 16920316902124161000,
              "timestamp": 1780411498790
            },
            {
              "tool": "read",
              "argsHash": 15576351455860832000,
              "timestamp": 1780411499059
            }
          ],
          "warningIssued": false,
          "warningReason": ""
        },
        "Atlas - Plan Executor:16": {
          "id": 16,
          "agentName": "Atlas - Plan Executor",
          "startedAtMs": 1780411383004,
          "toolCalls": 0,
          "consecutiveErrors": 0,
          "hardLimitHit": false,
          "lastSuccessTimeMs": 1780411383004,
          "recentToolCalls": [],
          "warningIssued": false,
          "warningReason": ""
        },
        "Atlas - Plan Executor:15": {
          "id": 15,
          "agentName": "Atlas - Plan Executor",
          "startedAtMs": 1780411382358,
          "toolCalls": 0,
          "consecutiveErrors": 0,
          "hardLimitHit": false,
          "lastSuccessTimeMs": 1780411382358,
          "recentToolCalls": [],
          "warningIssued": false,
          "warningReason": ""
        },
        "Atlas - Plan Executor:14": {
          "id": 14,
          "agentName": "Atlas - Plan Executor",
          "startedAtMs": 1780411305114,
          "toolCalls": 0,
          "consecutiveErrors": 0,
          "hardLimitHit": false,
          "lastSuccessTimeMs": 1780411305114,
          "recentToolCalls": [],
          "warningIssued": false,
          "warningReason": ""
        },
        "Atlas - Plan Executor:13": {
          "id": 13,
          "agentName": "Atlas - Plan Executor",
          "startedAtMs": 1780411305114,
          "toolCalls": 0,
          "consecutiveErrors": 0,
          "hardLimitHit": false,
          "lastSuccessTimeMs": 1780411305114,
          "recentToolCalls": [],
          "warningIssued": false,
          "warningReason": ""
        },
        "Atlas - Plan Executor:12": {
          "id": 12,
          "agentName": "Atlas - Plan Executor",
          "startedAtMs": 1780411305114,
          "toolCalls": 0,
          "consecutiveErrors": 0,
          "hardLimitHit": false,
          "lastSuccessTimeMs": 1780411305114,
          "recentToolCalls": [],
          "warningIssued": false,
          "warningReason": ""
        },
        "Atlas - Plan Executor:11": {
          "id": 11,
          "agentName": "Atlas - Plan Executor",
          "startedAtMs": 1780411305114,
          "toolCalls": 0,
          "consecutiveErrors": 0,
          "hardLimitHit": false,
          "lastSuccessTimeMs": 1780411305114,
          "recentToolCalls": [],
          "warningIssued": false,
          "warningReason": ""
        },
        "Atlas - Plan Executor:10": {
          "id": 10,
          "agentName": "Atlas - Plan Executor",
          "startedAtMs": 1780411305114,
          "toolCalls": 0,
          "consecutiveErrors": 0,
          "hardLimitHit": false,
          "lastSuccessTimeMs": 1780411305114,
          "recentToolCalls": [],
          "warningIssued": false,
          "warningReason": ""
        },
        "Atlas - Plan Executor:9": {
          "id": 9,
          "agentName": "Atlas - Plan Executor",
          "startedAtMs": 1780411305114,
          "toolCalls": 0,
          "consecutiveErrors": 0,
          "hardLimitHit": false,
          "lastSuccessTimeMs": 1780411305114,
          "recentToolCalls": [],
          "warningIssued": false,
          "warningReason": ""
        },
        "Atlas - Plan Executor:8": {
          "id": 8,
          "agentName": "Atlas - Plan Executor",
          "startedAtMs": 1780411305114,
          "toolCalls": 0,
          "consecutiveErrors": 0,
          "hardLimitHit": false,
          "lastSuccessTimeMs": 1780411305114,
          "recentToolCalls": [],
          "warningIssued": false,
          "warningReason": ""
        },
        "Atlas - Plan Executor:7": {
          "id": 7,
          "agentName": "Atlas - Plan Executor",
          "startedAtMs": 1780411305114,
          "toolCalls": 0,
          "consecutiveErrors": 0,
          "hardLimitHit": false,
          "lastSuccessTimeMs": 1780411305114,
          "recentToolCalls": [],
          "warningIssued": false,
          "warningReason": ""
        },
        "Sisyphus - Ultraworker:6": {
          "id": 6,
          "agentName": "Sisyphus - Ultraworker",
          "startedAtMs": 1780411305114,
          "toolCalls": 0,
          "consecutiveErrors": 0,
          "hardLimitHit": false,
          "lastSuccessTimeMs": 1780411305114,
          "recentToolCalls": [],
          "warningIssued": false,
          "warningReason": ""
        },
        "Sisyphus - Ultraworker:5": {
          "id": 5,
          "agentName": "Sisyphus - Ultraworker",
          "startedAtMs": 1780411305114,
          "toolCalls": 0,
          "consecutiveErrors": 0,
          "hardLimitHit": false,
          "lastSuccessTimeMs": 1780411305114,
          "recentToolCalls": [],
          "warningIssued": false,
          "warningReason": ""
        },
        "Sisyphus - Ultraworker:4": {
          "id": 4,
          "agentName": "Sisyphus - Ultraworker",
          "startedAtMs": 1780411305114,
          "toolCalls": 0,
          "consecutiveErrors": 0,
          "hardLimitHit": false,
          "lastSuccessTimeMs": 1780411305114,
          "recentToolCalls": [],
          "warningIssued": false,
          "warningReason": ""
        },
        "Sisyphus - Ultraworker:3": {
          "id": 3,
          "agentName": "Sisyphus - Ultraworker",
          "startedAtMs": 1780411305114,
          "toolCalls": 0,
          "consecutiveErrors": 0,
          "hardLimitHit": false,
          "lastSuccessTimeMs": 1780411305114,
          "recentToolCalls": [],
          "warningIssued": false,
          "warningReason": ""
        },
        "Sisyphus - Ultraworker:2": {
          "id": 2,
          "agentName": "Sisyphus - Ultraworker",
          "startedAtMs": 1780411305114,
          "toolCalls": 0,
          "consecutiveErrors": 0,
          "hardLimitHit": false,
          "lastSuccessTimeMs": 1780411305114,
          "recentToolCalls": [],
          "warningIssued": false,
          "warningReason": ""
        },
        "Sisyphus - Ultraworker:1": {
          "id": 1,
          "agentName": "Sisyphus - Ultraworker",
          "startedAtMs": 1780411305114,
          "toolCalls": 0,
          "consecutiveErrors": 0,
          "hardLimitHit": false,
          "lastSuccessTimeMs": 1780411305114,
          "recentToolCalls": [],
          "warningIssued": false,
          "warningReason": ""
        },
        "Atlas - Plan Executor:6": {
          "id": 6,
          "agentName": "Atlas - Plan Executor",
          "startedAtMs": 1780411305114,
          "toolCalls": 0,
          "consecutiveErrors": 0,
          "hardLimitHit": false,
          "lastSuccessTimeMs": 1780411305114,
          "recentToolCalls": [],
          "warningIssued": false,
          "warningReason": ""
        },
        "Atlas - Plan Executor:5": {
          "id": 5,
          "agentName": "Atlas - Plan Executor",
          "startedAtMs": 1780411305114,
          "toolCalls": 0,
          "consecutiveErrors": 0,
          "hardLimitHit": false,
          "lastSuccessTimeMs": 1780411305114,
          "recentToolCalls": [],
          "warningIssued": false,
          "warningReason": ""
        },
        "Atlas - Plan Executor:4": {
          "id": 4,
          "agentName": "Atlas - Plan Executor",
          "startedAtMs": 1780411305114,
          "toolCalls": 0,
          "consecutiveErrors": 0,
          "hardLimitHit": false,
          "lastSuccessTimeMs": 1780411305114,
          "recentToolCalls": [],
          "warningIssued": false,
          "warningReason": ""
        },
        "Atlas - Plan Executor:3": {
          "id": 3,
          "agentName": "Atlas - Plan Executor",
          "startedAtMs": 1780411305114,
          "toolCalls": 0,
          "consecutiveErrors": 0,
          "hardLimitHit": false,
          "lastSuccessTimeMs": 1780411305114,
          "recentToolCalls": [],
          "warningIssued": false,
          "warningReason": ""
        },
        "Atlas - Plan Executor:2": {
          "id": 2,
          "agentName": "Atlas - Plan Executor",
          "startedAtMs": 1780411305114,
          "toolCalls": 0,
          "consecutiveErrors": 0,
          "hardLimitHit": false,
          "lastSuccessTimeMs": 1780411305114,
          "recentToolCalls": [],
          "warningIssued": false,
          "warningReason": ""
        },
        "Atlas - Plan Executor:1": {
          "id": 1,
          "agentName": "Atlas - Plan Executor",
          "startedAtMs": 1780411305114,
          "toolCalls": 0,
          "consecutiveErrors": 0,
          "hardLimitHit": false,
          "lastSuccessTimeMs": 1780411305114,
          "recentToolCalls": [],
          "warningIssued": false,
          "warningReason": ""
        },
        "Prometheus - Plan Builder:7": {
          "id": 7,
          "agentName": "Prometheus - Plan Builder",
          "startedAtMs": 1780411305114,
          "toolCalls": 0,
          "consecutiveErrors": 0,
          "hardLimitHit": false,
          "lastSuccessTimeMs": 1780411305114,
          "recentToolCalls": [],
          "warningIssued": false,
          "warningReason": ""
        },
        "Prometheus - Plan Builder:6": {
          "id": 6,
          "agentName": "Prometheus - Plan Builder",
          "startedAtMs": 1780411305114,
          "toolCalls": 0,
          "consecutiveErrors": 0,
          "hardLimitHit": false,
          "lastSuccessTimeMs": 1780411305114,
          "recentToolCalls": [],
          "warningIssued": false,
          "warningReason": ""
        },
        "Prometheus - Plan Builder:5": {
          "id": 5,
          "agentName": "Prometheus - Plan Builder",
          "startedAtMs": 1780411305114,
          "toolCalls": 0,
          "consecutiveErrors": 0,
          "hardLimitHit": false,
          "lastSuccessTimeMs": 1780411305114,
          "recentToolCalls": [],
          "warningIssued": false,
          "warningReason": ""
        },
        "Prometheus - Plan Builder:4": {
          "id": 4,
          "agentName": "Prometheus - Plan Builder",
          "startedAtMs": 1780411305114,
          "toolCalls": 0,
          "consecutiveErrors": 0,
          "hardLimitHit": false,
          "lastSuccessTimeMs": 1780411305114,
          "recentToolCalls": [],
          "warningIssued": false,
          "warningReason": ""
        },
        "Prometheus - Plan Builder:3": {
          "id": 3,
          "agentName": "Prometheus - Plan Builder",
          "startedAtMs": 1780411305114,
          "toolCalls": 0,
          "consecutiveErrors": 0,
          "hardLimitHit": false,
          "lastSuccessTimeMs": 1780411305114,
          "recentToolCalls": [],
          "warningIssued": false,
          "warningReason": ""
        },
        "Prometheus - Plan Builder:2": {
          "id": 2,
          "agentName": "Prometheus - Plan Builder",
          "startedAtMs": 1780411305114,
          "toolCalls": 0,
          "consecutiveErrors": 0,
          "hardLimitHit": false,
          "lastSuccessTimeMs": 1780411305114,
          "recentToolCalls": [],
          "warningIssued": false,
          "warningReason": ""
        },
        "Prometheus - Plan Builder:1": {
          "id": 1,
          "agentName": "Prometheus - Plan Builder",
          "startedAtMs": 1780411305114,
          "toolCalls": 0,
          "consecutiveErrors": 0,
          "hardLimitHit": false,
          "lastSuccessTimeMs": 1780411305114,
          "recentToolCalls": [],
          "warningIssued": false,
          "warningReason": ""
        }
      },
      "lastCompactionHint": 0,
      "architectWriteCount": 0,
      "lastCoderDelegationTaskId": null,
      "currentTaskId": null,
      "turboMode": false,
      "gateLog": {},
      "reviewerCallCount": {},
      "lastGateFailure": null,
      "partialGateWarningsIssuedForTask": [
        "ses_178e189dfffe4D1vd3BAlugntC:unknown"
      ],
      "selfFixAttempted": false,
      "selfCodingWarnedAtCount": 0,
      "catastrophicPhaseWarnings": [],
      "lastPhaseCompleteTimestamp": 0,
      "lastPhaseCompletePhase": 0,
      "phaseAgentsDispatched": [
        "Prometheus - Plan Builder",
        "Atlas - Plan Executor",
        "Sisyphus - Ultraworker"
      ],
      "lastCompletedPhaseAgentsDispatched": [],
      "qaSkipCount": 0,
      "qaSkipTaskIds": [],
      "pendingAdvisoryMessages": [],
      "taskWorkflowStates": {},
      "scopeViolationDetected": false,
      "model_fallback_index": 0,
      "modelFallbackExhausted": false,
      "coderRevisions": 0,
      "revisionLimitHit": false,
      "fullAutoMode": false,
      "fullAutoInteractionCount": 0,
      "fullAutoDeadlockCount": 0,
      "fullAutoLastQuestionHash": null,
      "sessionRehydratedAt": 1780411305114
    },
    "ses_178dd7795ffe78UCewnoJjvwoP": {
      "agentName": "explore",
      "lastToolCallTime": 1780411305114,
      "lastAgentEventTime": 1780411305114,
      "delegationActive": false,
      "activeInvocationId": 1,
      "lastInvocationIdByAgent": {
        "explore": 1
      },
      "windows": {
        "explore:1": {
          "id": 1,
          "agentName": "explore",
          "startedAtMs": 1780411305114,
          "toolCalls": 0,
          "consecutiveErrors": 0,
          "hardLimitHit": false,
          "lastSuccessTimeMs": 1780411305114,
          "recentToolCalls": [],
          "warningIssued": false,
          "warningReason": ""
        }
      },
      "lastCompactionHint": 0,
      "architectWriteCount": 0,
      "lastCoderDelegationTaskId": null,
      "currentTaskId": null,
      "turboMode": false,
      "gateLog": {},
      "reviewerCallCount": {},
      "lastGateFailure": null,
      "partialGateWarningsIssuedForTask": [],
      "selfFixAttempted": false,
      "selfCodingWarnedAtCount": 0,
      "catastrophicPhaseWarnings": [],
      "lastPhaseCompleteTimestamp": 0,
      "lastPhaseCompletePhase": 0,
      "phaseAgentsDispatched": [
        "explore"
      ],
      "lastCompletedPhaseAgentsDispatched": [],
      "qaSkipCount": 0,
      "qaSkipTaskIds": [],
      "pendingAdvisoryMessages": [],
      "taskWorkflowStates": {},
      "scopeViolationDetected": false,
      "model_fallback_index": 0,
      "modelFallbackExhausted": false,
      "coderRevisions": 0,
      "revisionLimitHit": false,
      "fullAutoMode": false,
      "fullAutoInteractionCount": 0,
      "fullAutoDeadlockCount": 0,
      "fullAutoLastQuestionHash": null,
      "sessionRehydratedAt": 1780411305114
    },
    "ses_178d61460ffetLfLdnzIJfx1V1": {
      "agentName": "Metis - Plan Consultant",
      "lastToolCallTime": 1780411305114,
      "lastAgentEventTime": 1780411305114,
      "delegationActive": false,
      "activeInvocationId": 5,
      "lastInvocationIdByAgent": {
        "Metis - Plan Consultant": 5
      },
      "windows": {
        "Metis - Plan Consultant:5": {
          "id": 5,
          "agentName": "Metis - Plan Consultant",
          "startedAtMs": 1780411305114,
          "toolCalls": 0,
          "consecutiveErrors": 0,
          "hardLimitHit": false,
          "lastSuccessTimeMs": 1780411305114,
          "recentToolCalls": [],
          "warningIssued": false,
          "warningReason": ""
        },
        "Metis - Plan Consultant:4": {
          "id": 4,
          "agentName": "Metis - Plan Consultant",
          "startedAtMs": 1780411305114,
          "toolCalls": 0,
          "consecutiveErrors": 0,
          "hardLimitHit": false,
          "lastSuccessTimeMs": 1780411305114,
          "recentToolCalls": [],
          "warningIssued": false,
          "warningReason": ""
        },
        "Metis - Plan Consultant:3": {
          "id": 3,
          "agentName": "Metis - Plan Consultant",
          "startedAtMs": 1780411305114,
          "toolCalls": 0,
          "consecutiveErrors": 0,
          "hardLimitHit": false,
          "lastSuccessTimeMs": 1780411305114,
          "recentToolCalls": [],
          "warningIssued": false,
          "warningReason": ""
        },
        "Metis - Plan Consultant:2": {
          "id": 2,
          "agentName": "Metis - Plan Consultant",
          "startedAtMs": 1780411305114,
          "toolCalls": 0,
          "consecutiveErrors": 0,
          "hardLimitHit": false,
          "lastSuccessTimeMs": 1780411305114,
          "recentToolCalls": [],
          "warningIssued": false,
          "warningReason": ""
        },
        "Metis - Plan Consultant:1": {
          "id": 1,
          "agentName": "Metis - Plan Consultant",
          "startedAtMs": 1780411305114,
          "toolCalls": 0,
          "consecutiveErrors": 0,
          "hardLimitHit": false,
          "lastSuccessTimeMs": 1780411305114,
          "recentToolCalls": [],
          "warningIssued": false,
          "warningReason": ""
        }
      },
      "lastCompactionHint": 0,
      "architectWriteCount": 0,
      "lastCoderDelegationTaskId": null,
      "currentTaskId": null,
      "turboMode": false,
      "gateLog": {},
      "reviewerCallCount": {},
      "lastGateFailure": null,
      "partialGateWarningsIssuedForTask": [],
      "selfFixAttempted": false,
      "selfCodingWarnedAtCount": 0,
      "catastrophicPhaseWarnings": [],
      "lastPhaseCompleteTimestamp": 0,
      "lastPhaseCompletePhase": 0,
      "phaseAgentsDispatched": [
        "Metis - Plan Consultant"
      ],
      "lastCompletedPhaseAgentsDispatched": [],
      "qaSkipCount": 0,
      "qaSkipTaskIds": [],
      "pendingAdvisoryMessages": [],
      "taskWorkflowStates": {},
      "scopeViolationDetected": false,
      "model_fallback_index": 0,
      "modelFallbackExhausted": false,
      "coderRevisions": 0,
      "revisionLimitHit": false,
      "fullAutoMode": false,
      "fullAutoInteractionCount": 0,
      "fullAutoDeadlockCount": 0,
      "fullAutoLastQuestionHash": null,
      "sessionRehydratedAt": 1780411305114
    },
    "ses_178d5c3c1ffeFPqrXPM5DY1ogy": {
      "agentName": "explore",
      "lastToolCallTime": 1780411305114,
      "lastAgentEventTime": 1780411305114,
      "delegationActive": false,
      "activeInvocationId": 1,
      "lastInvocationIdByAgent": {
        "explore": 1
      },
      "windows": {
        "explore:1": {
          "id": 1,
          "agentName": "explore",
          "startedAtMs": 1780411305114,
          "toolCalls": 0,
          "consecutiveErrors": 0,
          "hardLimitHit": false,
          "lastSuccessTimeMs": 1780411305114,
          "recentToolCalls": [],
          "warningIssued": false,
          "warningReason": ""
        }
      },
      "lastCompactionHint": 0,
      "architectWriteCount": 0,
      "lastCoderDelegationTaskId": null,
      "currentTaskId": null,
      "turboMode": false,
      "gateLog": {},
      "reviewerCallCount": {},
      "lastGateFailure": null,
      "partialGateWarningsIssuedForTask": [],
      "selfFixAttempted": false,
      "selfCodingWarnedAtCount": 0,
      "catastrophicPhaseWarnings": [],
      "lastPhaseCompleteTimestamp": 0,
      "lastPhaseCompletePhase": 0,
      "phaseAgentsDispatched": [
        "explore"
      ],
      "lastCompletedPhaseAgentsDispatched": [],
      "qaSkipCount": 0,
      "qaSkipTaskIds": [],
      "pendingAdvisoryMessages": [],
      "taskWorkflowStates": {},
      "scopeViolationDetected": false,
      "model_fallback_index": 0,
      "modelFallbackExhausted": false,
      "coderRevisions": 0,
      "revisionLimitHit": false,
      "fullAutoMode": false,
      "fullAutoInteractionCount": 0,
      "fullAutoDeadlockCount": 0,
      "fullAutoLastQuestionHash": null,
      "sessionRehydratedAt": 1780411305114
    },
    "ses_178d5c392ffedbvkUIQi46ijpu": {
      "agentName": "explore",
      "lastToolCallTime": 1780411305114,
      "lastAgentEventTime": 1780411305114,
      "delegationActive": false,
      "activeInvocationId": 1,
      "lastInvocationIdByAgent": {
        "explore": 1
      },
      "windows": {
        "explore:1": {
          "id": 1,
          "agentName": "explore",
          "startedAtMs": 1780411305114,
          "toolCalls": 0,
          "consecutiveErrors": 0,
          "hardLimitHit": false,
          "lastSuccessTimeMs": 1780411305114,
          "recentToolCalls": [],
          "warningIssued": false,
          "warningReason": ""
        }
      },
      "lastCompactionHint": 0,
      "architectWriteCount": 0,
      "lastCoderDelegationTaskId": null,
      "currentTaskId": null,
      "turboMode": false,
      "gateLog": {},
      "reviewerCallCount": {},
      "lastGateFailure": null,
      "partialGateWarningsIssuedForTask": [],
      "selfFixAttempted": false,
      "selfCodingWarnedAtCount": 0,
      "catastrophicPhaseWarnings": [],
      "lastPhaseCompleteTimestamp": 0,
      "lastPhaseCompletePhase": 0,
      "phaseAgentsDispatched": [
        "explore"
      ],
      "lastCompletedPhaseAgentsDispatched": [],
      "qaSkipCount": 0,
      "qaSkipTaskIds": [],
      "pendingAdvisoryMessages": [],
      "taskWorkflowStates": {},
      "scopeViolationDetected": false,
      "model_fallback_index": 0,
      "modelFallbackExhausted": false,
      "coderRevisions": 0,
      "revisionLimitHit": false,
      "fullAutoMode": false,
      "fullAutoInteractionCount": 0,
      "fullAutoDeadlockCount": 0,
      "fullAutoLastQuestionHash": null,
      "sessionRehydratedAt": 1780411305114
    },
    "ses_178d5c360ffek2M3RX1EMGj1E2": {
      "agentName": "explore",
      "lastToolCallTime": 1780411305114,
      "lastAgentEventTime": 1780411305114,
      "delegationActive": false,
      "activeInvocationId": 1,
      "lastInvocationIdByAgent": {
        "explore": 1
      },
      "windows": {
        "explore:1": {
          "id": 1,
          "agentName": "explore",
          "startedAtMs": 1780411305114,
          "toolCalls": 0,
          "consecutiveErrors": 0,
          "hardLimitHit": false,
          "lastSuccessTimeMs": 1780411305114,
          "recentToolCalls": [],
          "warningIssued": false,
          "warningReason": ""
        }
      },
      "lastCompactionHint": 0,
      "architectWriteCount": 0,
      "lastCoderDelegationTaskId": null,
      "currentTaskId": null,
      "turboMode": false,
      "gateLog": {},
      "reviewerCallCount": {},
      "lastGateFailure": null,
      "partialGateWarningsIssuedForTask": [],
      "selfFixAttempted": false,
      "selfCodingWarnedAtCount": 0,
      "catastrophicPhaseWarnings": [],
      "lastPhaseCompleteTimestamp": 0,
      "lastPhaseCompletePhase": 0,
      "phaseAgentsDispatched": [
        "explore"
      ],
      "lastCompletedPhaseAgentsDispatched": [],
      "qaSkipCount": 0,
      "qaSkipTaskIds": [],
      "pendingAdvisoryMessages": [],
      "taskWorkflowStates": {},
      "scopeViolationDetected": false,
      "model_fallback_index": 0,
      "modelFallbackExhausted": false,
      "coderRevisions": 0,
      "revisionLimitHit": false,
      "fullAutoMode": false,
      "fullAutoInteractionCount": 0,
      "fullAutoDeadlockCount": 0,
      "fullAutoLastQuestionHash": null,
      "sessionRehydratedAt": 1780411305114
    },
    "ses_178c78078ffePxLxRBVP3cFNg8": {
      "agentName": "Momus - Plan Critic",
      "lastToolCallTime": 1780411305114,
      "lastAgentEventTime": 1780411305114,
      "delegationActive": false,
      "activeInvocationId": 1,
      "lastInvocationIdByAgent": {
        "critic": 1
      },
      "windows": {
        "critic:1": {
          "id": 1,
          "agentName": "critic",
          "startedAtMs": 1780411305114,
          "toolCalls": 0,
          "consecutiveErrors": 0,
          "hardLimitHit": false,
          "lastSuccessTimeMs": 1780411305114,
          "recentToolCalls": [],
          "warningIssued": false,
          "warningReason": ""
        }
      },
      "lastCompactionHint": 0,
      "architectWriteCount": 0,
      "lastCoderDelegationTaskId": null,
      "currentTaskId": null,
      "turboMode": false,
      "gateLog": {},
      "reviewerCallCount": {},
      "lastGateFailure": null,
      "partialGateWarningsIssuedForTask": [],
      "selfFixAttempted": false,
      "selfCodingWarnedAtCount": 0,
      "catastrophicPhaseWarnings": [],
      "lastPhaseCompleteTimestamp": 0,
      "lastPhaseCompletePhase": 0,
      "phaseAgentsDispatched": [
        "critic"
      ],
      "lastCompletedPhaseAgentsDispatched": [],
      "qaSkipCount": 0,
      "qaSkipTaskIds": [],
      "pendingAdvisoryMessages": [],
      "taskWorkflowStates": {},
      "scopeViolationDetected": false,
      "model_fallback_index": 0,
      "modelFallbackExhausted": false,
      "coderRevisions": 0,
      "revisionLimitHit": false,
      "fullAutoMode": false,
      "fullAutoInteractionCount": 0,
      "fullAutoDeadlockCount": 0,
      "fullAutoLastQuestionHash": null,
      "sessionRehydratedAt": 1780411305114
    },
    "ses_178bb5f9effeD79730cfx8SxAZ": {
      "agentName": "Momus - Plan Critic",
      "lastToolCallTime": 1780411305114,
      "lastAgentEventTime": 1780411305114,
      "delegationActive": false,
      "activeInvocationId": 1,
      "lastInvocationIdByAgent": {
        "critic": 1
      },
      "windows": {
        "critic:1": {
          "id": 1,
          "agentName": "critic",
          "startedAtMs": 1780411305114,
          "toolCalls": 0,
          "consecutiveErrors": 0,
          "hardLimitHit": false,
          "lastSuccessTimeMs": 1780411305114,
          "recentToolCalls": [],
          "warningIssued": false,
          "warningReason": ""
        }
      },
      "lastCompactionHint": 0,
      "architectWriteCount": 0,
      "lastCoderDelegationTaskId": null,
      "currentTaskId": null,
      "turboMode": false,
      "gateLog": {},
      "reviewerCallCount": {},
      "lastGateFailure": null,
      "partialGateWarningsIssuedForTask": [],
      "selfFixAttempted": false,
      "selfCodingWarnedAtCount": 0,
      "catastrophicPhaseWarnings": [],
      "lastPhaseCompleteTimestamp": 0,
      "lastPhaseCompletePhase": 0,
      "phaseAgentsDispatched": [
        "critic"
      ],
      "lastCompletedPhaseAgentsDispatched": [],
      "qaSkipCount": 0,
      "qaSkipTaskIds": [],
      "pendingAdvisoryMessages": [],
      "taskWorkflowStates": {},
      "scopeViolationDetected": false,
      "model_fallback_index": 0,
      "modelFallbackExhausted": false,
      "coderRevisions": 0,
      "revisionLimitHit": false,
      "fullAutoMode": false,
      "fullAutoInteractionCount": 0,
      "fullAutoDeadlockCount": 0,
      "fullAutoLastQuestionHash": null,
      "sessionRehydratedAt": 1780411305114
    },
    "ses_178b53c12ffehdA46tGbzK70ws": {
      "agentName": "Sisyphus-Junior",
      "lastToolCallTime": 1780411305114,
      "lastAgentEventTime": 1780411305114,
      "delegationActive": false,
      "activeInvocationId": 1,
      "lastInvocationIdByAgent": {
        "Sisyphus-Junior": 1
      },
      "windows": {
        "Sisyphus-Junior:1": {
          "id": 1,
          "agentName": "Sisyphus-Junior",
          "startedAtMs": 1780411305114,
          "toolCalls": 0,
          "consecutiveErrors": 0,
          "hardLimitHit": false,
          "lastSuccessTimeMs": 1780411305114,
          "recentToolCalls": [],
          "warningIssued": false,
          "warningReason": ""
        }
      },
      "lastCompactionHint": 0,
      "architectWriteCount": 0,
      "lastCoderDelegationTaskId": null,
      "currentTaskId": null,
      "turboMode": false,
      "gateLog": {},
      "reviewerCallCount": {},
      "lastGateFailure": null,
      "partialGateWarningsIssuedForTask": [],
      "selfFixAttempted": false,
      "selfCodingWarnedAtCount": 0,
      "catastrophicPhaseWarnings": [],
      "lastPhaseCompleteTimestamp": 0,
      "lastPhaseCompletePhase": 0,
      "phaseAgentsDispatched": [
        "Sisyphus-Junior"
      ],
      "lastCompletedPhaseAgentsDispatched": [],
      "qaSkipCount": 0,
      "qaSkipTaskIds": [],
      "pendingAdvisoryMessages": [],
      "taskWorkflowStates": {},
      "scopeViolationDetected": false,
      "model_fallback_index": 0,
      "modelFallbackExhausted": false,
      "coderRevisions": 0,
      "revisionLimitHit": false,
      "fullAutoMode": false,
      "fullAutoInteractionCount": 0,
      "fullAutoDeadlockCount": 0,
      "fullAutoLastQuestionHash": null,
      "sessionRehydratedAt": 1780411305114
    },
    "ses_178abd8f3ffeS4xgCbRlfLVMrv": {
      "agentName": "Sisyphus-Junior",
      "lastToolCallTime": 1780411305114,
      "lastAgentEventTime": 1780411305114,
      "delegationActive": false,
      "activeInvocationId": 1,
      "lastInvocationIdByAgent": {
        "Sisyphus-Junior": 1
      },
      "windows": {
        "Sisyphus-Junior:1": {
          "id": 1,
          "agentName": "Sisyphus-Junior",
          "startedAtMs": 1780411305114,
          "toolCalls": 0,
          "consecutiveErrors": 0,
          "hardLimitHit": false,
          "lastSuccessTimeMs": 1780411305114,
          "recentToolCalls": [],
          "warningIssued": false,
          "warningReason": ""
        }
      },
      "lastCompactionHint": 0,
      "architectWriteCount": 0,
      "lastCoderDelegationTaskId": null,
      "currentTaskId": null,
      "turboMode": false,
      "gateLog": {},
      "reviewerCallCount": {},
      "lastGateFailure": null,
      "partialGateWarningsIssuedForTask": [],
      "selfFixAttempted": false,
      "selfCodingWarnedAtCount": 0,
      "catastrophicPhaseWarnings": [],
      "lastPhaseCompleteTimestamp": 0,
      "lastPhaseCompletePhase": 0,
      "phaseAgentsDispatched": [
        "Sisyphus-Junior"
      ],
      "lastCompletedPhaseAgentsDispatched": [],
      "qaSkipCount": 0,
      "qaSkipTaskIds": [],
      "pendingAdvisoryMessages": [],
      "taskWorkflowStates": {},
      "scopeViolationDetected": false,
      "model_fallback_index": 0,
      "modelFallbackExhausted": false,
      "coderRevisions": 0,
      "revisionLimitHit": false,
      "fullAutoMode": false,
      "fullAutoInteractionCount": 0,
      "fullAutoDeadlockCount": 0,
      "fullAutoLastQuestionHash": null,
      "sessionRehydratedAt": 1780411305114
    },
    "ses_178a941ecffe6SuctiUtqJDahX": {
      "agentName": "orchestrator",
      "lastToolCallTime": 1780411305114,
      "lastAgentEventTime": 1780411305114,
      "delegationActive": false,
      "activeInvocationId": 1,
      "lastInvocationIdByAgent": {
        "orchestrator": 1
      },
      "windows": {
        "orchestrator:1": {
          "id": 1,
          "agentName": "orchestrator",
          "startedAtMs": 1780411305114,
          "toolCalls": 0,
          "consecutiveErrors": 0,
          "hardLimitHit": false,
          "lastSuccessTimeMs": 1780411305114,
          "recentToolCalls": [],
          "warningIssued": false,
          "warningReason": ""
        }
      },
      "lastCompactionHint": 0,
      "architectWriteCount": 0,
      "lastCoderDelegationTaskId": null,
      "currentTaskId": null,
      "turboMode": false,
      "gateLog": {},
      "reviewerCallCount": {},
      "lastGateFailure": null,
      "partialGateWarningsIssuedForTask": [],
      "selfFixAttempted": false,
      "selfCodingWarnedAtCount": 0,
      "catastrophicPhaseWarnings": [],
      "lastPhaseCompleteTimestamp": 0,
      "lastPhaseCompletePhase": 0,
      "phaseAgentsDispatched": [
        "orchestrator"
      ],
      "lastCompletedPhaseAgentsDispatched": [],
      "qaSkipCount": 0,
      "qaSkipTaskIds": [],
      "pendingAdvisoryMessages": [],
      "taskWorkflowStates": {},
      "scopeViolationDetected": false,
      "model_fallback_index": 0,
      "modelFallbackExhausted": false,
      "coderRevisions": 0,
      "revisionLimitHit": false,
      "fullAutoMode": false,
      "fullAutoInteractionCount": 0,
      "fullAutoDeadlockCount": 0,
      "fullAutoLastQuestionHash": null,
      "sessionRehydratedAt": 1780411305114
    },
    "ses_1789226a5ffeewrncTH4m5SLkH": {
      "agentName": "Sisyphus-Junior",
      "lastToolCallTime": 1780411305114,
      "lastAgentEventTime": 1780411305114,
      "delegationActive": false,
      "activeInvocationId": 1,
      "lastInvocationIdByAgent": {
        "Sisyphus-Junior": 1
      },
      "windows": {
        "Sisyphus-Junior:1": {
          "id": 1,
          "agentName": "Sisyphus-Junior",
          "startedAtMs": 1780411305114,
          "toolCalls": 0,
          "consecutiveErrors": 0,
          "hardLimitHit": false,
          "lastSuccessTimeMs": 1780411305114,
          "recentToolCalls": [],
          "warningIssued": false,
          "warningReason": ""
        }
      },
      "lastCompactionHint": 0,
      "architectWriteCount": 0,
      "lastCoderDelegationTaskId": null,
      "currentTaskId": null,
      "turboMode": false,
      "gateLog": {},
      "reviewerCallCount": {},
      "lastGateFailure": null,
      "partialGateWarningsIssuedForTask": [],
      "selfFixAttempted": false,
      "selfCodingWarnedAtCount": 0,
      "catastrophicPhaseWarnings": [],
      "lastPhaseCompleteTimestamp": 0,
      "lastPhaseCompletePhase": 0,
      "phaseAgentsDispatched": [
        "Sisyphus-Junior"
      ],
      "lastCompletedPhaseAgentsDispatched": [],
      "qaSkipCount": 0,
      "qaSkipTaskIds": [],
      "pendingAdvisoryMessages": [],
      "taskWorkflowStates": {},
      "scopeViolationDetected": false,
      "model_fallback_index": 0,
      "modelFallbackExhausted": false,
      "coderRevisions": 0,
      "revisionLimitHit": false,
      "fullAutoMode": false,
      "fullAutoInteractionCount": 0,
      "fullAutoDeadlockCount": 0,
      "fullAutoLastQuestionHash": null,
      "sessionRehydratedAt": 1780411305114
    },
    "ses_1788542ccffed8DqqTG5Ro76AV": {
      "agentName": "Sisyphus-Junior",
      "lastToolCallTime": 1780411305114,
      "lastAgentEventTime": 1780411305114,
      "delegationActive": false,
      "activeInvocationId": 1,
      "lastInvocationIdByAgent": {
        "Sisyphus-Junior": 1
      },
      "windows": {
        "Sisyphus-Junior:1": {
          "id": 1,
          "agentName": "Sisyphus-Junior",
          "startedAtMs": 1780411305114,
          "toolCalls": 0,
          "consecutiveErrors": 0,
          "hardLimitHit": false,
          "lastSuccessTimeMs": 1780411305114,
          "recentToolCalls": [],
          "warningIssued": false,
          "warningReason": ""
        }
      },
      "lastCompactionHint": 0,
      "architectWriteCount": 0,
      "lastCoderDelegationTaskId": null,
      "currentTaskId": null,
      "turboMode": false,
      "gateLog": {},
      "reviewerCallCount": {},
      "lastGateFailure": null,
      "partialGateWarningsIssuedForTask": [],
      "selfFixAttempted": false,
      "selfCodingWarnedAtCount": 0,
      "catastrophicPhaseWarnings": [],
      "lastPhaseCompleteTimestamp": 0,
      "lastPhaseCompletePhase": 0,
      "phaseAgentsDispatched": [
        "Sisyphus-Junior"
      ],
      "lastCompletedPhaseAgentsDispatched": [],
      "qaSkipCount": 0,
      "qaSkipTaskIds": [],
      "pendingAdvisoryMessages": [],
      "taskWorkflowStates": {},
      "scopeViolationDetected": false,
      "model_fallback_index": 0,
      "modelFallbackExhausted": false,
      "coderRevisions": 0,
      "revisionLimitHit": false,
      "fullAutoMode": false,
      "fullAutoInteractionCount": 0,
      "fullAutoDeadlockCount": 0,
      "fullAutoLastQuestionHash": null,
      "sessionRehydratedAt": 1780411305114
    },
    "ses_1787e7758ffeeC9gPa3G7StW5d": {
      "agentName": "Sisyphus-Junior",
      "lastToolCallTime": 1780411305114,
      "lastAgentEventTime": 1780411305114,
      "delegationActive": false,
      "activeInvocationId": 1,
      "lastInvocationIdByAgent": {
        "Sisyphus-Junior": 1
      },
      "windows": {
        "Sisyphus-Junior:1": {
          "id": 1,
          "agentName": "Sisyphus-Junior",
          "startedAtMs": 1780411305114,
          "toolCalls": 0,
          "consecutiveErrors": 0,
          "hardLimitHit": false,
          "lastSuccessTimeMs": 1780411305114,
          "recentToolCalls": [],
          "warningIssued": false,
          "warningReason": ""
        }
      },
      "lastCompactionHint": 0,
      "architectWriteCount": 0,
      "lastCoderDelegationTaskId": null,
      "currentTaskId": null,
      "turboMode": false,
      "gateLog": {},
      "reviewerCallCount": {},
      "lastGateFailure": null,
      "partialGateWarningsIssuedForTask": [],
      "selfFixAttempted": false,
      "selfCodingWarnedAtCount": 0,
      "catastrophicPhaseWarnings": [],
      "lastPhaseCompleteTimestamp": 0,
      "lastPhaseCompletePhase": 0,
      "phaseAgentsDispatched": [
        "Sisyphus-Junior"
      ],
      "lastCompletedPhaseAgentsDispatched": [],
      "qaSkipCount": 0,
      "qaSkipTaskIds": [],
      "pendingAdvisoryMessages": [],
      "taskWorkflowStates": {},
      "scopeViolationDetected": false,
      "model_fallback_index": 0,
      "modelFallbackExhausted": false,
      "coderRevisions": 0,
      "revisionLimitHit": false,
      "fullAutoMode": false,
      "fullAutoInteractionCount": 0,
      "fullAutoDeadlockCount": 0,
      "fullAutoLastQuestionHash": null,
      "sessionRehydratedAt": 1780411305114
    },
    "ses_1787e7538ffeorwqm8aezrM1id": {
      "agentName": "Sisyphus-Junior",
      "lastToolCallTime": 1780411305114,
      "lastAgentEventTime": 1780411305114,
      "delegationActive": false,
      "activeInvocationId": 1,
      "lastInvocationIdByAgent": {
        "Sisyphus-Junior": 1
      },
      "windows": {
        "Sisyphus-Junior:1": {
          "id": 1,
          "agentName": "Sisyphus-Junior",
          "startedAtMs": 1780411305114,
          "toolCalls": 0,
          "consecutiveErrors": 0,
          "hardLimitHit": false,
          "lastSuccessTimeMs": 1780411305114,
          "recentToolCalls": [],
          "warningIssued": false,
          "warningReason": ""
        }
      },
      "lastCompactionHint": 0,
      "architectWriteCount": 0,
      "lastCoderDelegationTaskId": null,
      "currentTaskId": null,
      "turboMode": false,
      "gateLog": {},
      "reviewerCallCount": {},
      "lastGateFailure": null,
      "partialGateWarningsIssuedForTask": [],
      "selfFixAttempted": false,
      "selfCodingWarnedAtCount": 0,
      "catastrophicPhaseWarnings": [],
      "lastPhaseCompleteTimestamp": 0,
      "lastPhaseCompletePhase": 0,
      "phaseAgentsDispatched": [
        "Sisyphus-Junior"
      ],
      "lastCompletedPhaseAgentsDispatched": [],
      "qaSkipCount": 0,
      "qaSkipTaskIds": [],
      "pendingAdvisoryMessages": [],
      "taskWorkflowStates": {},
      "scopeViolationDetected": false,
      "model_fallback_index": 0,
      "modelFallbackExhausted": false,
      "coderRevisions": 0,
      "revisionLimitHit": false,
      "fullAutoMode": false,
      "fullAutoInteractionCount": 0,
      "fullAutoDeadlockCount": 0,
      "fullAutoLastQuestionHash": null,
      "sessionRehydratedAt": 1780411305114
    },
    "ses_1787a80fbffeLlft4WmclFLxyF": {
      "agentName": "Sisyphus-Junior",
      "lastToolCallTime": 1780411305114,
      "lastAgentEventTime": 1780411305114,
      "delegationActive": false,
      "activeInvocationId": 1,
      "lastInvocationIdByAgent": {
        "Sisyphus-Junior": 1
      },
      "windows": {
        "Sisyphus-Junior:1": {
          "id": 1,
          "agentName": "Sisyphus-Junior",
          "startedAtMs": 1780411305114,
          "toolCalls": 0,
          "consecutiveErrors": 0,
          "hardLimitHit": false,
          "lastSuccessTimeMs": 1780411305114,
          "recentToolCalls": [],
          "warningIssued": false,
          "warningReason": ""
        }
      },
      "lastCompactionHint": 0,
      "architectWriteCount": 0,
      "lastCoderDelegationTaskId": null,
      "currentTaskId": null,
      "turboMode": false,
      "gateLog": {},
      "reviewerCallCount": {},
      "lastGateFailure": null,
      "partialGateWarningsIssuedForTask": [],
      "selfFixAttempted": false,
      "selfCodingWarnedAtCount": 0,
      "catastrophicPhaseWarnings": [],
      "lastPhaseCompleteTimestamp": 0,
      "lastPhaseCompletePhase": 0,
      "phaseAgentsDispatched": [
        "Sisyphus-Junior"
      ],
      "lastCompletedPhaseAgentsDispatched": [],
      "qaSkipCount": 0,
      "qaSkipTaskIds": [],
      "pendingAdvisoryMessages": [],
      "taskWorkflowStates": {},
      "scopeViolationDetected": false,
      "model_fallback_index": 0,
      "modelFallbackExhausted": false,
      "coderRevisions": 0,
      "revisionLimitHit": false,
      "fullAutoMode": false,
      "fullAutoInteractionCount": 0,
      "fullAutoDeadlockCount": 0,
      "fullAutoLastQuestionHash": null,
      "sessionRehydratedAt": 1780411305114
    },
    "ses_17878a413ffeSkPhj22UNZZe3U": {
      "agentName": "oracle",
      "lastToolCallTime": 1780411305114,
      "lastAgentEventTime": 1780411305114,
      "delegationActive": false,
      "activeInvocationId": 1,
      "lastInvocationIdByAgent": {
        "oracle": 1
      },
      "windows": {
        "oracle:1": {
          "id": 1,
          "agentName": "oracle",
          "startedAtMs": 1780411305114,
          "toolCalls": 0,
          "consecutiveErrors": 0,
          "hardLimitHit": false,
          "lastSuccessTimeMs": 1780411305114,
          "recentToolCalls": [],
          "warningIssued": false,
          "warningReason": ""
        }
      },
      "lastCompactionHint": 0,
      "architectWriteCount": 0,
      "lastCoderDelegationTaskId": null,
      "currentTaskId": null,
      "turboMode": false,
      "gateLog": {},
      "reviewerCallCount": {},
      "lastGateFailure": null,
      "partialGateWarningsIssuedForTask": [],
      "selfFixAttempted": false,
      "selfCodingWarnedAtCount": 0,
      "catastrophicPhaseWarnings": [],
      "lastPhaseCompleteTimestamp": 0,
      "lastPhaseCompletePhase": 0,
      "phaseAgentsDispatched": [
        "oracle"
      ],
      "lastCompletedPhaseAgentsDispatched": [],
      "qaSkipCount": 0,
      "qaSkipTaskIds": [],
      "pendingAdvisoryMessages": [],
      "taskWorkflowStates": {},
      "scopeViolationDetected": false,
      "model_fallback_index": 0,
      "modelFallbackExhausted": false,
      "coderRevisions": 0,
      "revisionLimitHit": false,
      "fullAutoMode": false,
      "fullAutoInteractionCount": 0,
      "fullAutoDeadlockCount": 0,
      "fullAutoLastQuestionHash": null,
      "sessionRehydratedAt": 1780411305114
    },
    "ses_178728cdcffeoyY4Mt10M7EAwQ": {
      "agentName": "Sisyphus-Junior",
      "lastToolCallTime": 1780411305114,
      "lastAgentEventTime": 1780411305114,
      "delegationActive": false,
      "activeInvocationId": 1,
      "lastInvocationIdByAgent": {
        "Sisyphus-Junior": 1
      },
      "windows": {
        "Sisyphus-Junior:1": {
          "id": 1,
          "agentName": "Sisyphus-Junior",
          "startedAtMs": 1780411305114,
          "toolCalls": 0,
          "consecutiveErrors": 0,
          "hardLimitHit": false,
          "lastSuccessTimeMs": 1780411305114,
          "recentToolCalls": [],
          "warningIssued": false,
          "warningReason": ""
        }
      },
      "lastCompactionHint": 0,
      "architectWriteCount": 0,
      "lastCoderDelegationTaskId": null,
      "currentTaskId": null,
      "turboMode": false,
      "gateLog": {},
      "reviewerCallCount": {},
      "lastGateFailure": null,
      "partialGateWarningsIssuedForTask": [],
      "selfFixAttempted": false,
      "selfCodingWarnedAtCount": 0,
      "catastrophicPhaseWarnings": [],
      "lastPhaseCompleteTimestamp": 0,
      "lastPhaseCompletePhase": 0,
      "phaseAgentsDispatched": [
        "Sisyphus-Junior"
      ],
      "lastCompletedPhaseAgentsDispatched": [],
      "qaSkipCount": 0,
      "qaSkipTaskIds": [],
      "pendingAdvisoryMessages": [],
      "taskWorkflowStates": {},
      "scopeViolationDetected": false,
      "model_fallback_index": 0,
      "modelFallbackExhausted": false,
      "coderRevisions": 0,
      "revisionLimitHit": false,
      "fullAutoMode": false,
      "fullAutoInteractionCount": 0,
      "fullAutoDeadlockCount": 0,
      "fullAutoLastQuestionHash": null,
      "sessionRehydratedAt": 1780411305114
    },
    "ses_178676ecaffe7wpebhPkI370f9": {
      "agentName": "Sisyphus-Junior",
      "lastToolCallTime": 1780411305114,
      "lastAgentEventTime": 1780411305114,
      "delegationActive": false,
      "activeInvocationId": 1,
      "lastInvocationIdByAgent": {
        "Sisyphus-Junior": 1
      },
      "windows": {
        "Sisyphus-Junior:1": {
          "id": 1,
          "agentName": "Sisyphus-Junior",
          "startedAtMs": 1780411305114,
          "toolCalls": 0,
          "consecutiveErrors": 0,
          "hardLimitHit": false,
          "lastSuccessTimeMs": 1780411305114,
          "recentToolCalls": [],
          "warningIssued": false,
          "warningReason": ""
        }
      },
      "lastCompactionHint": 0,
      "architectWriteCount": 0,
      "lastCoderDelegationTaskId": null,
      "currentTaskId": null,
      "turboMode": false,
      "gateLog": {},
      "reviewerCallCount": {},
      "lastGateFailure": null,
      "partialGateWarningsIssuedForTask": [],
      "selfFixAttempted": false,
      "selfCodingWarnedAtCount": 0,
      "catastrophicPhaseWarnings": [],
      "lastPhaseCompleteTimestamp": 0,
      "lastPhaseCompletePhase": 0,
      "phaseAgentsDispatched": [
        "Sisyphus-Junior"
      ],
      "lastCompletedPhaseAgentsDispatched": [],
      "qaSkipCount": 0,
      "qaSkipTaskIds": [],
      "pendingAdvisoryMessages": [],
      "taskWorkflowStates": {},
      "scopeViolationDetected": false,
      "model_fallback_index": 0,
      "modelFallbackExhausted": false,
      "coderRevisions": 0,
      "revisionLimitHit": false,
      "fullAutoMode": false,
      "fullAutoInteractionCount": 0,
      "fullAutoDeadlockCount": 0,
      "fullAutoLastQuestionHash": null,
      "sessionRehydratedAt": 1780411305114
    },
    "ses_178628648ffel4hmSIAf3etPy5": {
      "agentName": "Sisyphus-Junior",
      "lastToolCallTime": 1780411305114,
      "lastAgentEventTime": 1780411305114,
      "delegationActive": false,
      "activeInvocationId": 1,
      "lastInvocationIdByAgent": {
        "Sisyphus-Junior": 1
      },
      "windows": {
        "Sisyphus-Junior:1": {
          "id": 1,
          "agentName": "Sisyphus-Junior",
          "startedAtMs": 1780411305114,
          "toolCalls": 0,
          "consecutiveErrors": 0,
          "hardLimitHit": false,
          "lastSuccessTimeMs": 1780411305114,
          "recentToolCalls": [],
          "warningIssued": false,
          "warningReason": ""
        }
      },
      "lastCompactionHint": 0,
      "architectWriteCount": 0,
      "lastCoderDelegationTaskId": null,
      "currentTaskId": null,
      "turboMode": false,
      "gateLog": {},
      "reviewerCallCount": {},
      "lastGateFailure": null,
      "partialGateWarningsIssuedForTask": [],
      "selfFixAttempted": false,
      "selfCodingWarnedAtCount": 0,
      "catastrophicPhaseWarnings": [],
      "lastPhaseCompleteTimestamp": 0,
      "lastPhaseCompletePhase": 0,
      "phaseAgentsDispatched": [
        "Sisyphus-Junior"
      ],
      "lastCompletedPhaseAgentsDispatched": [],
      "qaSkipCount": 0,
      "qaSkipTaskIds": [],
      "pendingAdvisoryMessages": [],
      "taskWorkflowStates": {},
      "scopeViolationDetected": false,
      "model_fallback_index": 0,
      "modelFallbackExhausted": false,
      "coderRevisions": 0,
      "revisionLimitHit": false,
      "fullAutoMode": false,
      "fullAutoInteractionCount": 0,
      "fullAutoDeadlockCount": 0,
      "fullAutoLastQuestionHash": null,
      "sessionRehydratedAt": 1780411305114
    },
    "ses_1786182dcffe69Zr7lZ4Kms518": {
      "agentName": "orchestrator",
      "lastToolCallTime": 1780411305114,
      "lastAgentEventTime": 1780411305114,
      "delegationActive": false,
      "activeInvocationId": 1,
      "lastInvocationIdByAgent": {
        "orchestrator": 1
      },
      "windows": {
        "orchestrator:1": {
          "id": 1,
          "agentName": "orchestrator",
          "startedAtMs": 1780411305114,
          "toolCalls": 0,
          "consecutiveErrors": 0,
          "hardLimitHit": false,
          "lastSuccessTimeMs": 1780411305114,
          "recentToolCalls": [],
          "warningIssued": false,
          "warningReason": ""
        }
      },
      "lastCompactionHint": 0,
      "architectWriteCount": 0,
      "lastCoderDelegationTaskId": null,
      "currentTaskId": null,
      "turboMode": false,
      "gateLog": {},
      "reviewerCallCount": {},
      "lastGateFailure": null,
      "partialGateWarningsIssuedForTask": [],
      "selfFixAttempted": false,
      "selfCodingWarnedAtCount": 0,
      "catastrophicPhaseWarnings": [],
      "lastPhaseCompleteTimestamp": 0,
      "lastPhaseCompletePhase": 0,
      "phaseAgentsDispatched": [
        "orchestrator"
      ],
      "lastCompletedPhaseAgentsDispatched": [],
      "qaSkipCount": 0,
      "qaSkipTaskIds": [],
      "pendingAdvisoryMessages": [],
      "taskWorkflowStates": {},
      "scopeViolationDetected": false,
      "model_fallback_index": 0,
      "modelFallbackExhausted": false,
      "coderRevisions": 0,
      "revisionLimitHit": false,
      "fullAutoMode": false,
      "fullAutoInteractionCount": 0,
      "fullAutoDeadlockCount": 0,
      "fullAutoLastQuestionHash": null,
      "sessionRehydratedAt": 1780411305114
    },
    "ses_1785a3476ffelz6FA649fbhLXU": {
      "agentName": "oracle",
      "lastToolCallTime": 1780411305114,
      "lastAgentEventTime": 1780411305114,
      "delegationActive": false,
      "activeInvocationId": 1,
      "lastInvocationIdByAgent": {
        "oracle": 1
      },
      "windows": {
        "oracle:1": {
          "id": 1,
          "agentName": "oracle",
          "startedAtMs": 1780411305114,
          "toolCalls": 0,
          "consecutiveErrors": 0,
          "hardLimitHit": false,
          "lastSuccessTimeMs": 1780411305114,
          "recentToolCalls": [],
          "warningIssued": false,
          "warningReason": ""
        }
      },
      "lastCompactionHint": 0,
      "architectWriteCount": 0,
      "lastCoderDelegationTaskId": null,
      "currentTaskId": null,
      "turboMode": false,
      "gateLog": {},
      "reviewerCallCount": {},
      "lastGateFailure": null,
      "partialGateWarningsIssuedForTask": [],
      "selfFixAttempted": false,
      "selfCodingWarnedAtCount": 0,
      "catastrophicPhaseWarnings": [],
      "lastPhaseCompleteTimestamp": 0,
      "lastPhaseCompletePhase": 0,
      "phaseAgentsDispatched": [
        "oracle"
      ],
      "lastCompletedPhaseAgentsDispatched": [],
      "qaSkipCount": 0,
      "qaSkipTaskIds": [],
      "pendingAdvisoryMessages": [],
      "taskWorkflowStates": {},
      "scopeViolationDetected": false,
      "model_fallback_index": 0,
      "modelFallbackExhausted": false,
      "coderRevisions": 0,
      "revisionLimitHit": false,
      "fullAutoMode": false,
      "fullAutoInteractionCount": 0,
      "fullAutoDeadlockCount": 0,
      "fullAutoLastQuestionHash": null,
      "sessionRehydratedAt": 1780411305114
    },
    "ses_1785a3199ffeLlqK2zWgwJgg1B": {
      "agentName": "Sisyphus-Junior",
      "lastToolCallTime": 1780411305114,
      "lastAgentEventTime": 1780411305114,
      "delegationActive": false,
      "activeInvocationId": 1,
      "lastInvocationIdByAgent": {
        "Sisyphus-Junior": 1
      },
      "windows": {
        "Sisyphus-Junior:1": {
          "id": 1,
          "agentName": "Sisyphus-Junior",
          "startedAtMs": 1780411305114,
          "toolCalls": 0,
          "consecutiveErrors": 0,
          "hardLimitHit": false,
          "lastSuccessTimeMs": 1780411305114,
          "recentToolCalls": [],
          "warningIssued": false,
          "warningReason": ""
        }
      },
      "lastCompactionHint": 0,
      "architectWriteCount": 0,
      "lastCoderDelegationTaskId": null,
      "currentTaskId": null,
      "turboMode": false,
      "gateLog": {},
      "reviewerCallCount": {},
      "lastGateFailure": null,
      "partialGateWarningsIssuedForTask": [],
      "selfFixAttempted": false,
      "selfCodingWarnedAtCount": 0,
      "catastrophicPhaseWarnings": [],
      "lastPhaseCompleteTimestamp": 0,
      "lastPhaseCompletePhase": 0,
      "phaseAgentsDispatched": [
        "Sisyphus-Junior"
      ],
      "lastCompletedPhaseAgentsDispatched": [],
      "qaSkipCount": 0,
      "qaSkipTaskIds": [],
      "pendingAdvisoryMessages": [],
      "taskWorkflowStates": {},
      "scopeViolationDetected": false,
      "model_fallback_index": 0,
      "modelFallbackExhausted": false,
      "coderRevisions": 0,
      "revisionLimitHit": false,
      "fullAutoMode": false,
      "fullAutoInteractionCount": 0,
      "fullAutoDeadlockCount": 0,
      "fullAutoLastQuestionHash": null,
      "sessionRehydratedAt": 1780411305114
    },
    "ses_1785a2eafffeJ5yEIdkGOa81f2": {
      "agentName": "Sisyphus-Junior",
      "lastToolCallTime": 1780411305114,
      "lastAgentEventTime": 1780411305114,
      "delegationActive": false,
      "activeInvocationId": 1,
      "lastInvocationIdByAgent": {
        "Sisyphus-Junior": 1
      },
      "windows": {
        "Sisyphus-Junior:1": {
          "id": 1,
          "agentName": "Sisyphus-Junior",
          "startedAtMs": 1780411305114,
          "toolCalls": 0,
          "consecutiveErrors": 0,
          "hardLimitHit": false,
          "lastSuccessTimeMs": 1780411305114,
          "recentToolCalls": [],
          "warningIssued": false,
          "warningReason": ""
        }
      },
      "lastCompactionHint": 0,
      "architectWriteCount": 0,
      "lastCoderDelegationTaskId": null,
      "currentTaskId": null,
      "turboMode": false,
      "gateLog": {},
      "reviewerCallCount": {},
      "lastGateFailure": null,
      "partialGateWarningsIssuedForTask": [],
      "selfFixAttempted": false,
      "selfCodingWarnedAtCount": 0,
      "catastrophicPhaseWarnings": [],
      "lastPhaseCompleteTimestamp": 0,
      "lastPhaseCompletePhase": 0,
      "phaseAgentsDispatched": [
        "Sisyphus-Junior"
      ],
      "lastCompletedPhaseAgentsDispatched": [],
      "qaSkipCount": 0,
      "qaSkipTaskIds": [],
      "pendingAdvisoryMessages": [],
      "taskWorkflowStates": {},
      "scopeViolationDetected": false,
      "model_fallback_index": 0,
      "modelFallbackExhausted": false,
      "coderRevisions": 0,
      "revisionLimitHit": false,
      "fullAutoMode": false,
      "fullAutoInteractionCount": 0,
      "fullAutoDeadlockCount": 0,
      "fullAutoLastQuestionHash": null,
      "sessionRehydratedAt": 1780411305114
    },
    "ses_1785993cfffeDUuXeczEd63fxd": {
      "agentName": "Sisyphus-Junior",
      "lastToolCallTime": 1780411305114,
      "lastAgentEventTime": 1780411305114,
      "delegationActive": false,
      "activeInvocationId": 1,
      "lastInvocationIdByAgent": {
        "Sisyphus-Junior": 1
      },
      "windows": {
        "Sisyphus-Junior:1": {
          "id": 1,
          "agentName": "Sisyphus-Junior",
          "startedAtMs": 1780411305114,
          "toolCalls": 0,
          "consecutiveErrors": 0,
          "hardLimitHit": false,
          "lastSuccessTimeMs": 1780411305114,
          "recentToolCalls": [],
          "warningIssued": false,
          "warningReason": ""
        }
      },
      "lastCompactionHint": 0,
      "architectWriteCount": 0,
      "lastCoderDelegationTaskId": null,
      "currentTaskId": null,
      "turboMode": false,
      "gateLog": {},
      "reviewerCallCount": {},
      "lastGateFailure": null,
      "partialGateWarningsIssuedForTask": [],
      "selfFixAttempted": false,
      "selfCodingWarnedAtCount": 0,
      "catastrophicPhaseWarnings": [],
      "lastPhaseCompleteTimestamp": 0,
      "lastPhaseCompletePhase": 0,
      "phaseAgentsDispatched": [
        "Sisyphus-Junior"
      ],
      "lastCompletedPhaseAgentsDispatched": [],
      "qaSkipCount": 0,
      "qaSkipTaskIds": [],
      "pendingAdvisoryMessages": [],
      "taskWorkflowStates": {},
      "scopeViolationDetected": false,
      "model_fallback_index": 0,
      "modelFallbackExhausted": false,
      "coderRevisions": 0,
      "revisionLimitHit": false,
      "fullAutoMode": false,
      "fullAutoInteractionCount": 0,
      "fullAutoDeadlockCount": 0,
      "fullAutoLastQuestionHash": null,
      "sessionRehydratedAt": 1780411305114
    },
    "ses_17840457effeELX05ICmnKbr7n": {
      "agentName": "explore",
      "lastToolCallTime": 1780411305114,
      "lastAgentEventTime": 1780411305114,
      "delegationActive": false,
      "activeInvocationId": 1,
      "lastInvocationIdByAgent": {
        "explore": 1
      },
      "windows": {
        "explore:1": {
          "id": 1,
          "agentName": "explore",
          "startedAtMs": 1780411305114,
          "toolCalls": 0,
          "consecutiveErrors": 0,
          "hardLimitHit": false,
          "lastSuccessTimeMs": 1780411305114,
          "recentToolCalls": [],
          "warningIssued": false,
          "warningReason": ""
        }
      },
      "lastCompactionHint": 0,
      "architectWriteCount": 0,
      "lastCoderDelegationTaskId": null,
      "currentTaskId": null,
      "turboMode": false,
      "gateLog": {},
      "reviewerCallCount": {},
      "lastGateFailure": null,
      "partialGateWarningsIssuedForTask": [],
      "selfFixAttempted": false,
      "selfCodingWarnedAtCount": 0,
      "catastrophicPhaseWarnings": [],
      "lastPhaseCompleteTimestamp": 0,
      "lastPhaseCompletePhase": 0,
      "phaseAgentsDispatched": [
        "explore"
      ],
      "lastCompletedPhaseAgentsDispatched": [],
      "qaSkipCount": 0,
      "qaSkipTaskIds": [],
      "pendingAdvisoryMessages": [],
      "taskWorkflowStates": {},
      "scopeViolationDetected": false,
      "model_fallback_index": 0,
      "modelFallbackExhausted": false,
      "coderRevisions": 0,
      "revisionLimitHit": false,
      "fullAutoMode": false,
      "fullAutoInteractionCount": 0,
      "fullAutoDeadlockCount": 0,
      "fullAutoLastQuestionHash": null,
      "sessionRehydratedAt": 1780411305114
    },
    "ses_178360d02ffe2mXxvL2pQOnKoh": {
      "agentName": "Sisyphus-Junior",
      "lastToolCallTime": 1780411305114,
      "lastAgentEventTime": 1780411305114,
      "delegationActive": false,
      "activeInvocationId": 1,
      "lastInvocationIdByAgent": {
        "Sisyphus-Junior": 1
      },
      "windows": {
        "Sisyphus-Junior:1": {
          "id": 1,
          "agentName": "Sisyphus-Junior",
          "startedAtMs": 1780411305114,
          "toolCalls": 0,
          "consecutiveErrors": 0,
          "hardLimitHit": false,
          "lastSuccessTimeMs": 1780411305114,
          "recentToolCalls": [],
          "warningIssued": false,
          "warningReason": ""
        }
      },
      "lastCompactionHint": 0,
      "architectWriteCount": 0,
      "lastCoderDelegationTaskId": null,
      "currentTaskId": null,
      "turboMode": false,
      "gateLog": {},
      "reviewerCallCount": {},
      "lastGateFailure": null,
      "partialGateWarningsIssuedForTask": [],
      "selfFixAttempted": false,
      "selfCodingWarnedAtCount": 0,
      "catastrophicPhaseWarnings": [],
      "lastPhaseCompleteTimestamp": 0,
      "lastPhaseCompletePhase": 0,
      "phaseAgentsDispatched": [
        "Sisyphus-Junior"
      ],
      "lastCompletedPhaseAgentsDispatched": [],
      "qaSkipCount": 0,
      "qaSkipTaskIds": [],
      "pendingAdvisoryMessages": [],
      "taskWorkflowStates": {},
      "scopeViolationDetected": false,
      "model_fallback_index": 0,
      "modelFallbackExhausted": false,
      "coderRevisions": 0,
      "revisionLimitHit": false,
      "fullAutoMode": false,
      "fullAutoInteractionCount": 0,
      "fullAutoDeadlockCount": 0,
      "fullAutoLastQuestionHash": null,
      "sessionRehydratedAt": 1780411305114
    },
    "ses_1782a4defffeXFRU8kEhQPtEnC": {
      "agentName": "orchestrator",
      "lastToolCallTime": 1780411305114,
      "lastAgentEventTime": 1780411305114,
      "delegationActive": false,
      "activeInvocationId": 1,
      "lastInvocationIdByAgent": {
        "orchestrator": 1
      },
      "windows": {
        "orchestrator:1": {
          "id": 1,
          "agentName": "orchestrator",
          "startedAtMs": 1780411305114,
          "toolCalls": 0,
          "consecutiveErrors": 0,
          "hardLimitHit": false,
          "lastSuccessTimeMs": 1780411305114,
          "recentToolCalls": [],
          "warningIssued": false,
          "warningReason": ""
        }
      },
      "lastCompactionHint": 0,
      "architectWriteCount": 0,
      "lastCoderDelegationTaskId": null,
      "currentTaskId": null,
      "turboMode": false,
      "gateLog": {},
      "reviewerCallCount": {},
      "lastGateFailure": null,
      "partialGateWarningsIssuedForTask": [],
      "selfFixAttempted": false,
      "selfCodingWarnedAtCount": 0,
      "catastrophicPhaseWarnings": [],
      "lastPhaseCompleteTimestamp": 0,
      "lastPhaseCompletePhase": 0,
      "phaseAgentsDispatched": [
        "orchestrator"
      ],
      "lastCompletedPhaseAgentsDispatched": [],
      "qaSkipCount": 0,
      "qaSkipTaskIds": [],
      "pendingAdvisoryMessages": [],
      "taskWorkflowStates": {},
      "scopeViolationDetected": false,
      "model_fallback_index": 0,
      "modelFallbackExhausted": false,
      "coderRevisions": 0,
      "revisionLimitHit": false,
      "fullAutoMode": false,
      "fullAutoInteractionCount": 0,
      "fullAutoDeadlockCount": 0,
      "fullAutoLastQuestionHash": null,
      "sessionRehydratedAt": 1780411305114
    },
    "ses_1776eacc3ffebuCoQfn4uXiCWf": {
      "agentName": "Sisyphus-Junior",
      "lastToolCallTime": 1780411305114,
      "lastAgentEventTime": 1780411305114,
      "delegationActive": false,
      "activeInvocationId": 1,
      "lastInvocationIdByAgent": {
        "Sisyphus-Junior": 1
      },
      "windows": {
        "Sisyphus-Junior:1": {
          "id": 1,
          "agentName": "Sisyphus-Junior",
          "startedAtMs": 1780411305114,
          "toolCalls": 0,
          "consecutiveErrors": 0,
          "hardLimitHit": false,
          "lastSuccessTimeMs": 1780411305114,
          "recentToolCalls": [],
          "warningIssued": false,
          "warningReason": ""
        }
      },
      "lastCompactionHint": 0,
      "architectWriteCount": 0,
      "lastCoderDelegationTaskId": null,
      "currentTaskId": null,
      "turboMode": false,
      "gateLog": {},
      "reviewerCallCount": {},
      "lastGateFailure": null,
      "partialGateWarningsIssuedForTask": [],
      "selfFixAttempted": false,
      "selfCodingWarnedAtCount": 0,
      "catastrophicPhaseWarnings": [],
      "lastPhaseCompleteTimestamp": 0,
      "lastPhaseCompletePhase": 0,
      "phaseAgentsDispatched": [
        "Sisyphus-Junior"
      ],
      "lastCompletedPhaseAgentsDispatched": [],
      "qaSkipCount": 0,
      "qaSkipTaskIds": [],
      "pendingAdvisoryMessages": [],
      "taskWorkflowStates": {},
      "scopeViolationDetected": false,
      "model_fallback_index": 0,
      "modelFallbackExhausted": false,
      "coderRevisions": 0,
      "revisionLimitHit": false,
      "fullAutoMode": false,
      "fullAutoInteractionCount": 0,
      "fullAutoDeadlockCount": 0,
      "fullAutoLastQuestionHash": null,
      "sessionRehydratedAt": 1780411305114
    },
    "ses_1776d5536ffeYwa4LJORKdu0cI": {
      "agentName": "Sisyphus-Junior",
      "lastToolCallTime": 1780411305114,
      "lastAgentEventTime": 1780411305114,
      "delegationActive": false,
      "activeInvocationId": 1,
      "lastInvocationIdByAgent": {
        "Sisyphus-Junior": 1
      },
      "windows": {
        "Sisyphus-Junior:1": {
          "id": 1,
          "agentName": "Sisyphus-Junior",
          "startedAtMs": 1780411305114,
          "toolCalls": 0,
          "consecutiveErrors": 0,
          "hardLimitHit": false,
          "lastSuccessTimeMs": 1780411305114,
          "recentToolCalls": [],
          "warningIssued": false,
          "warningReason": ""
        }
      },
      "lastCompactionHint": 0,
      "architectWriteCount": 0,
      "lastCoderDelegationTaskId": null,
      "currentTaskId": null,
      "turboMode": false,
      "gateLog": {},
      "reviewerCallCount": {},
      "lastGateFailure": null,
      "partialGateWarningsIssuedForTask": [],
      "selfFixAttempted": false,
      "selfCodingWarnedAtCount": 0,
      "catastrophicPhaseWarnings": [],
      "lastPhaseCompleteTimestamp": 0,
      "lastPhaseCompletePhase": 0,
      "phaseAgentsDispatched": [
        "Sisyphus-Junior"
      ],
      "lastCompletedPhaseAgentsDispatched": [],
      "qaSkipCount": 0,
      "qaSkipTaskIds": [],
      "pendingAdvisoryMessages": [],
      "taskWorkflowStates": {},
      "scopeViolationDetected": false,
      "model_fallback_index": 0,
      "modelFallbackExhausted": false,
      "coderRevisions": 0,
      "revisionLimitHit": false,
      "fullAutoMode": false,
      "fullAutoInteractionCount": 0,
      "fullAutoDeadlockCount": 0,
      "fullAutoLastQuestionHash": null,
      "sessionRehydratedAt": 1780411305114
    },
    "ses_1776cb0e9ffe6pbBzD6nEWFQQD": {
      "agentName": "coder",
      "lastToolCallTime": 1780411305114,
      "lastAgentEventTime": 1780411305114,
      "delegationActive": false,
      "activeInvocationId": 1,
      "lastInvocationIdByAgent": {
        "coder": 1
      },
      "windows": {
        "coder:1": {
          "id": 1,
          "agentName": "coder",
          "startedAtMs": 1780411305114,
          "toolCalls": 0,
          "consecutiveErrors": 0,
          "hardLimitHit": false,
          "lastSuccessTimeMs": 1780411305114,
          "recentToolCalls": [],
          "warningIssued": false,
          "warningReason": ""
        }
      },
      "lastCompactionHint": 0,
      "architectWriteCount": 0,
      "lastCoderDelegationTaskId": null,
      "currentTaskId": null,
      "turboMode": false,
      "gateLog": {},
      "reviewerCallCount": {},
      "lastGateFailure": null,
      "partialGateWarningsIssuedForTask": [],
      "selfFixAttempted": false,
      "selfCodingWarnedAtCount": 0,
      "catastrophicPhaseWarnings": [],
      "lastPhaseCompleteTimestamp": 0,
      "lastPhaseCompletePhase": 0,
      "phaseAgentsDispatched": [
        "coder"
      ],
      "lastCompletedPhaseAgentsDispatched": [],
      "qaSkipCount": 0,
      "qaSkipTaskIds": [],
      "pendingAdvisoryMessages": [],
      "taskWorkflowStates": {},
      "scopeViolationDetected": false,
      "model_fallback_index": 0,
      "modelFallbackExhausted": false,
      "coderRevisions": 0,
      "revisionLimitHit": false,
      "fullAutoMode": false,
      "fullAutoInteractionCount": 0,
      "fullAutoDeadlockCount": 0,
      "fullAutoLastQuestionHash": null,
      "sessionRehydratedAt": 1780411305114
    },
    "ses_17751632affeOsNNROpeAqjFbt": {
      "agentName": "coder",
      "lastToolCallTime": 1780411305114,
      "lastAgentEventTime": 1780411305114,
      "delegationActive": false,
      "activeInvocationId": 1,
      "lastInvocationIdByAgent": {
        "coder": 1
      },
      "windows": {
        "coder:1": {
          "id": 1,
          "agentName": "coder",
          "startedAtMs": 1780411305114,
          "toolCalls": 0,
          "consecutiveErrors": 0,
          "hardLimitHit": false,
          "lastSuccessTimeMs": 1780411305114,
          "recentToolCalls": [],
          "warningIssued": false,
          "warningReason": ""
        }
      },
      "lastCompactionHint": 0,
      "architectWriteCount": 0,
      "lastCoderDelegationTaskId": null,
      "currentTaskId": null,
      "turboMode": false,
      "gateLog": {},
      "reviewerCallCount": {},
      "lastGateFailure": null,
      "partialGateWarningsIssuedForTask": [],
      "selfFixAttempted": false,
      "selfCodingWarnedAtCount": 0,
      "catastrophicPhaseWarnings": [],
      "lastPhaseCompleteTimestamp": 0,
      "lastPhaseCompletePhase": 0,
      "phaseAgentsDispatched": [
        "coder"
      ],
      "lastCompletedPhaseAgentsDispatched": [],
      "qaSkipCount": 0,
      "qaSkipTaskIds": [],
      "pendingAdvisoryMessages": [],
      "taskWorkflowStates": {},
      "scopeViolationDetected": false,
      "model_fallback_index": 0,
      "modelFallbackExhausted": false,
      "coderRevisions": 0,
      "revisionLimitHit": false,
      "fullAutoMode": false,
      "fullAutoInteractionCount": 0,
      "fullAutoDeadlockCount": 0,
      "fullAutoLastQuestionHash": null,
      "sessionRehydratedAt": 1780411305114
    }
  }
}